finary/__init__.py
finary/excel.py
finary/matha.py
finary-0.1.2.dist-info/METADATA
finary-0.1.2.dist-info/WHEEL
finary-0.1.2.dist-info/RECORD
