Metadata-Version: 2.1
Name: finary
Version: 0.1.2
Summary: Finary se compose de différents sous-modules ayant tous pour objectif d'augmenter la productivité d'un actuaire dans ses tâches du quotidien.
Author: Mathieu Clavier
Author-email: mathieu.clavier@outlook.com
Requires-Python: >=3.8,<4.0
Classifier: Programming Language :: Python :: 3
Classifier: Programming Language :: Python :: 3.8
Classifier: Programming Language :: Python :: 3.9
Classifier: Programming Language :: Python :: 3.10
Classifier: Programming Language :: Python :: 3.11
Requires-Dist: numpy (>=1.24.1,<2.0.0)
Requires-Dist: openpyxl (>=3.0.10,<4.0.0)
Requires-Dist: pandas (>=1.5.3,<2.0.0)
